./.gitignore
./.python-version
./1120_process.log
./CAD-mpc简单实现.mp4
./PKG-INFO
./README (2).md
./README.md
./autocad_manager.py
./db_manager.py
./language.json
./main.py
./package_name
./pyproject.toml
./requirements.txt
./server.py
./server.spec
./uv.lock
iflow_mcp_zh19980811_autocad_mcp_server-0.1.0.dist-info/METADATA
iflow_mcp_zh19980811_autocad_mcp_server-0.1.0.dist-info/WHEEL
iflow_mcp_zh19980811_autocad_mcp_server-0.1.0.dist-info/entry_points.txt
iflow_mcp_zh19980811_autocad_mcp_server-0.1.0.dist-info/RECORD
