Metadata-Version: 2.4
Name: iflow-mcp_zh19980811_autocad-mcp-server
Version: 0.1.0
Summary: AutoCAD MCP Server - Natural language control of AutoCAD drawings
Requires-Python: >=3.10
Requires-Dist: mcp[cli]>=1.4.1
Requires-Dist: sqlalchemy>=2.0.39
Provides-Extra: windows
Requires-Dist: comtypes>=1.4.10; extra == 'windows'
Requires-Dist: pyautocad>=0.2.0; extra == 'windows'
Requires-Dist: pywin32>=309; extra == 'windows'
